volant/__init__.py
volant/py.typed
volant-0.0.1.dist-info/WHEEL
volant-0.0.1.dist-info/METADATA
volant-0.0.1.dist-info/RECORD
